netpyx/__init__.py
netpyx/http_client.py
netpyx-1.0.1.dist-info/licenses/LICENSE
netpyx-1.0.1.dist-info/METADATA
netpyx-1.0.1.dist-info/WHEEL
netpyx-1.0.1.dist-info/top_level.txt
netpyx-1.0.1.dist-info/RECORD
